img2art/__init__.py
img2art/cli.py
img2art/utils.py
img2art-0.4.3.dist-info/METADATA
img2art-0.4.3.dist-info/WHEEL
img2art-0.4.3.dist-info/entry_points.txt
img2art-0.4.3.dist-info/RECORD
