Metadata-Version: 2.1
Name: img2art
Version: 0.4.3
Summary: 
License: MIT
Author: Asthestarsfalll
Author-email: 1186454801@qq.com
Requires-Python: >=3.8,<4.0
Classifier: License :: OSI Approved :: MIT License
Classifier: Programming Language :: Python :: 3
Classifier: Programming Language :: Python :: 3.8
Classifier: Programming Language :: Python :: 3.9
Classifier: Programming Language :: Python :: 3.10
Classifier: Programming Language :: Python :: 3.11
Classifier: Programming Language :: Python :: 3.12
Requires-Dist: numpy
Requires-Dist: opencv-python
Requires-Dist: typer (>=0.15.4,<0.16.0)
